openscap_report/__init__.py
openscap_report/cli.py
openscap_report/debug_settings.py
openscap_report/dataclasses/__init__.py
openscap_report/dataclasses/dataclasses.py
openscap_report/report_generators/__init__.py
openscap_report/report_generators/exceptions.py
openscap_report/report_generators/html.py
openscap_report/report_generators/json.py
openscap_report/report_generators/report_generator.py
openscap_report/report_generators/html_templates/base_report.html
openscap_report/report_generators/html_templates/cpe_graph.html
openscap_report/report_generators/html_templates/evaluation_characteristics.html
openscap_report/report_generators/html_templates/oval_definition_detail.html
openscap_report/report_generators/html_templates/oval_graph.html
openscap_report/report_generators/html_templates/profile_info.html
openscap_report/report_generators/html_templates/remedations.html
openscap_report/report_generators/html_templates/rule_detail.html
openscap_report/report_generators/html_templates/rule_results.html
openscap_report/report_generators/html_templates/rules_overview.html
openscap_report/report_generators/html_templates/score_bar.html
openscap_report/report_generators/html_templates/search_input.html
openscap_report/report_generators/html_templates/severity_of_failed_rules.html
openscap_report/report_generators/html_templates/summary_banner.html
openscap_report/report_generators/html_templates/template_report.html
openscap_report/report_generators/html_templates/assets/fonts/webfonts/fa-solid-900.woff
openscap_report/report_generators/html_templates/assets/fonts/webfonts/fa-solid-900.woff2
openscap_report/report_generators/html_templates/assets/pficon/pficon.woff
openscap_report/report_generators/html_templates/assets/pficon/pficon.woff2
openscap_report/report_generators/html_templates/css/patternfly.css
openscap_report/report_generators/html_templates/css/style.css
openscap_report/report_generators/html_templates/js/debug_script.js
openscap_report-1.0.0.dist-info/LICENSE
openscap_report-1.0.0.dist-info/LICENSE.spdx
openscap_report-1.0.0.dist-info/METADATA
openscap_report-1.0.0.dist-info/WHEEL
openscap_report-1.0.0.dist-info/entry_points.txt
openscap_report-1.0.0.dist-info/top_level.txt
openscap_report-1.0.0.dist-info/RECORD
