Metadata-Version: 2.1
Name: openscap-report
Version: 1.0.0
Summary: Tool for generating report from results of oscap scan.
Home-page: https://github.com/OpenSCAP/oscap-report
Author: Jan Rodak
Author-email: jrodak@redhat.com
License: LGPL-2.1 License
Requires-Python: >=3.6
License-File: LICENSE
License-File: LICENSE.spdx
Requires-Dist: lxml
Requires-Dist: jinja2
